etcd_register/__init__.py
etcd_register/etcd/__init__.py
etcd_register/etcd/client.py
etcd_register/http/__init__.py
etcd_register/http/invoke.py
etcd_register/proto/__init__.py
etcd_register/proto/invoke.proto
etcd_register/proto/invoke_pb2.py
etcd_register/proto/invoke_pb2_grpc.py
etcd_register/proto/rpc.proto
etcd_register/proto/rpc_pb2.py
etcd_register/proto/rpc_pb2_grpc.py
etcd_register/resolver/__init__.py
etcd_register/resolver/register.py
etcd_register/rpc/__init__.py
etcd_register/rpc/invoke.py
etcd_register/util/__init__.py
etcd_register/util/config.py
etcd_register-0.0.11.data/data/invoke.proto
etcd_register-0.0.11.dist-info/METADATA
etcd_register-0.0.11.dist-info/WHEEL
etcd_register-0.0.11.dist-info/top_level.txt
etcd_register-0.0.11.dist-info/RECORD
